ioscreen/__init__.py
ioscreen/asyn.py
ioscreen/main.py
ioscreen/meaasge.py
ioscreen/ping.py
ioscreen/sync.py
ioscreen/util.py
ioscreen/coremedia/AudioStream.py
ioscreen/coremedia/CMFormatDescription.py
ioscreen/coremedia/CMSampleBuffer.py
ioscreen/coremedia/CMTime.py
ioscreen/coremedia/CMclock.py
ioscreen/coremedia/__init__.py
ioscreen/coremedia/common.py
ioscreen/coremedia/consumer.py
ioscreen/coremedia/gstreamer.py
ioscreen/coremedia/rtspserver.py
ioscreen/coremedia/serialize.py
ioscreen/coremedia/wav.py
ioscreen-1.1.0.dev9.dist-info/AUTHORS
ioscreen-1.1.0.dev9.dist-info/LICENSE
ioscreen-1.1.0.dev9.dist-info/METADATA
ioscreen-1.1.0.dev9.dist-info/WHEEL
ioscreen-1.1.0.dev9.dist-info/entry_points.txt
ioscreen-1.1.0.dev9.dist-info/pbr.json
ioscreen-1.1.0.dev9.dist-info/top_level.txt
ioscreen-1.1.0.dev9.dist-info/RECORD
