Metadata-Version: 2.1
Name: ioscreen
Version: 1.1.0.dev9
Summary: UNKNOWN
Home-page: https://github.com/YueChen-C/ios-screen-record
Author: chenpeijie
Author-email: cpjsf@163.com
License: MIT
Platform: UNKNOWN
Classifier: Environment :: Console
Classifier: Intended Audience :: Developers
Classifier: Operating System :: POSIX
Classifier: Programming Language :: Python :: 3.7
Classifier: Topic :: Software Development :: Libraries :: Python Modules
Requires-Python: >=3.7
Requires-Dist: PyGObject (==3.38.0)
Requires-Dist: PyGObject-stubs (==0.0.2)
Requires-Dist: pyusb (==1.1.1)
